helios_rl/__init__.py
helios_rl/config.py
helios_rl/config_local.py
helios_rl/adapters/__init__.py
helios_rl/agents/__init__.py
helios_rl/agents/agent_abstract.py
helios_rl/agents/neural_q_agent.py
helios_rl/agents/random_agent.py
helios_rl/agents/table_q_agent.py
helios_rl/benchmark/benchmark_config.py
helios_rl/benchmark/benchmark_config_local.py
helios_rl/benchmark/run.py
helios_rl/encoders/__init__.py
helios_rl/encoders/encoder_abstract.py
helios_rl/encoders/observable_objects_encoded.py
helios_rl/encoders/poss_actions_encoded.py
helios_rl/encoders/poss_state_encoded.py
helios_rl/encoders/prior_actions_encoded.py
helios_rl/encoders/sentence_transformer_MiniLM_L6v2.py
helios_rl/environment_setup/helios_info.py
helios_rl/environment_setup/imports.py
helios_rl/environment_setup/results_table.py
helios_rl/evaluation/combined_variance_visual.py
helios_rl/evaluation/convergence_measure.py
helios_rl/evaluation/tabular_output.py
helios_rl/evaluation/visual_output.py
helios_rl/experiments/observed_states.py
helios_rl/experiments/standard.py
helios_rl/experiments/standard_exp_samp.py
helios_rl/hierarchies/helios_instr_input.py
helios_rl/hierarchies/helios_instruction_following.py
helios_rl/hierarchies/helios_instruction_search.py
helios_rl/hierarchies/helios_instruction_search_mlp.py
helios_rl/hierarchies/supervised_instruction_following.py
helios_rl/hierarchies/unsupervised_instruction_following.py
helios_rl/interaction_loops/batch_offline.py
helios_rl/interaction_loops/standard.py
helios_rl/interaction_loops/sub_goals.py
helios_rl/reporting/standard_report.py
helios_rl-1.3.26.dist-info/LICENSE
helios_rl-1.3.26.dist-info/METADATA
helios_rl-1.3.26.dist-info/WHEEL
helios_rl-1.3.26.dist-info/top_level.txt
helios_rl-1.3.26.dist-info/RECORD
